yahoomail/__init__.py
yahoomail-1.1.1.1.dist-info/METADATA
yahoomail-1.1.1.1.dist-info/WHEEL
yahoomail-1.1.1.1.dist-info/top_level.txt
yahoomail-1.1.1.1.dist-info/RECORD
