Metadata-Version: 2.1
Name: yahoomail
Version: 1.1.1.1
Summary: A high-performance, async Yahoo Mail login automator.
Home-page: https://github.com/anarchy223/yahoomail
Author: anarchy223
License: CC BY-NC-SA 4.0
Classifier: Programming Language :: Python :: 3
Classifier: License :: Free For Home Use
Classifier: Intended Audience :: Developers
Classifier: Operating System :: OS Independent
Classifier: Topic :: Software Development :: Libraries :: Python Modules
Requires-Python: >=3.7
Requires-Dist: httpx>=0.24.0
Requires-Dist: h2>=4.1.0
